model/__init__.py
model/example.csv
model/synfrag.py
model/synfrag_finetune.py
model/synfrag_pretrain.py
synfrag-1.0.0.data/data/checkpoints/synfrag_default.pth
synfrag-1.0.0.data/data/data/test_dataset/TS1.csv
synfrag-1.0.0.data/data/data/test_dataset/TS2.csv
synfrag-1.0.0.data/data/data/test_dataset/TS3.csv
synfrag-1.0.0.data/data/data/test_dataset/TSA.csv
synfrag-1.0.0.data/data/data/test_dataset/TSB.csv
synfrag-1.0.0.dist-info/licenses/LICENSE.txt
synfrag-1.0.0.dist-info/METADATA
synfrag-1.0.0.dist-info/WHEEL
synfrag-1.0.0.dist-info/entry_points.txt
synfrag-1.0.0.dist-info/top_level.txt
synfrag-1.0.0.dist-info/RECORD
