Metadata-Version: 2.4
Name: synfrag
Version: 1.0.0
Summary: SynFrag: A Synthetic Accessibility Predictor based Fragment Assembly autoRegressive pretrain
Home-page: https://github.com/simmzx/SynFrag
Author: Xiang Zhang
Author-email: 776206454@qq.com
License: MIT
Project-URL: Bug Reports, https://github.com/simmzx/SynFrag/issues
Project-URL: Source, https://github.com/simmzx/SynFrag
Project-URL: Documentation, https://github.com/simmzx/SynFrag/docs
Keywords: chemistry,molecular,synthesizability,synthetic accessibility,fragment assembly,deep learning,graph neural networks,cheminformatics,drug discovery,SMILES
Platform: any
Classifier: Development Status :: 4 - Beta
Classifier: Intended Audience :: Science/Research
Classifier: Intended Audience :: Developers
Classifier: License :: OSI Approved :: MIT License
Classifier: Programming Language :: Python :: 3
Classifier: Programming Language :: Python :: 3.8
Classifier: Programming Language :: Python :: 3.9
Classifier: Programming Language :: Python :: 3.10
Classifier: Programming Language :: Python :: 3.11
Classifier: Topic :: Scientific/Engineering :: Chemistry
Classifier: Topic :: Scientific/Engineering :: Artificial Intelligence
Classifier: Topic :: Software Development :: Libraries :: Python Modules
Requires-Python: >=3.8
License-File: LICENSE.txt
Provides-Extra: tensorflow
Requires-Dist: tensorflow<3.0.0,>=2.10.0; extra == "tensorflow"
Provides-Extra: dev
Requires-Dist: pytest>=6.0.0; extra == "dev"
Requires-Dist: pytest-cov>=2.0.0; extra == "dev"
Requires-Dist: black>=22.0.0; extra == "dev"
Requires-Dist: flake8>=4.0.0; extra == "dev"
Requires-Dist: mypy>=0.910; extra == "dev"
Provides-Extra: docs
Requires-Dist: sphinx>=4.0.0; extra == "docs"
Requires-Dist: sphinx-rtd-theme>=1.0.0; extra == "docs"
Requires-Dist: nbsphinx>=0.8.0; extra == "docs"
Dynamic: author
Dynamic: author-email
Dynamic: classifier
Dynamic: description
Dynamic: description-content-type
Dynamic: home-page
Dynamic: keywords
Dynamic: license
Dynamic: license-file
Dynamic: platform
Dynamic: project-url
Dynamic: provides-extra
Dynamic: requires-python
Dynamic: summary
